aivatar_project_api/__init__.py
aivatar_project_api/config_io.py
aivatar_project_api/constants.py
aivatar_project_api/core.py
aivatar_project_api/logger.py
aivatar_project_api/proj_requester.py
aivatar_project_api/configs/__init__.py
aivatar_project_api/configs/network.json
aivatar_project_api/configs/network_test.json
aivatar_project_api/test/__init__.py
aivatar_project_api/test/test_core.py
aivatar_project_api/test/test_imports.py
aivatar_project_api-0.2.0.dist-info/METADATA
aivatar_project_api-0.2.0.dist-info/WHEEL
aivatar_project_api-0.2.0.dist-info/top_level.txt
aivatar_project_api-0.2.0.dist-info/RECORD
